[
  {

    "City": "Vegas",
    "Category": "All",
    "checkin":[
      [0, 88978],
      [1, 56643],
      [2, 35848],
      [3, 24766],
      [4, 17101],
      [5, 20063],
      [6, 28937],
      [7, 58412],
      [8, 89146],
      [9, 121794],
      [10, 161755],
      [11, 249117],
      [12, 316554],
      [13, 292750],
      [14, 253110],
      [15, 228895],
      [16, 227228],
      [17, 271568],
      [18, 327024],
      [19, 328867],
      [20, 280812],
      [21, 221102],
      [22, 154870],
      [23, 118390]
    ],
    "food":[
      [0, 28208],
      [1, 18347],
      [2, 12939],
      [3, 9479],
      [4, 5993],
      [5, 6053],
      [6, 11866],
      [7, 25711],
      [8, 39912],
      [9, 56520],
      [10, 78130],
      [11, 139369],
      [12, 189026],
      [13, 164153],
      [14, 128851],
      [15, 107143],
      [16, 103898],
      [17, 133589],
      [18, 172384],
      [19, 182709],
      [20, 154073],
      [21, 108414],
      [22, 62801],
      [23, 39352]
    ]
  },
  {
    "City": "Charlotte",
    "Category": "All",
    "checkin":[
      [0, 403],
      [1, 613],
      [2, 1744],
      [3, 5300],
      [4, 8985],
      [5, 14086],
      [6, 14979],
      [7, 17748],
      [8, 29305],
      [9, 46682],
      [10, 40889],
      [11, 29582],
      [12, 26172],
      [13, 26239],
      [14, 34455],
      [15, 46754],
      [16, 49669],
      [17, 37238],
      [18, 25006],
      [19, 13289],
      [20, 7570],
      [21, 3972],
      [22, 1957],
      [23, 790]
    ],
    "food":[
      [0, 218],
      [1, 198],
      [2, 333],
      [3, 1545],
      [4, 4260],
      [5, 7549],
      [6, 8450],
      [7, 9270],
      [8, 18133],
      [9, 30969],
      [10, 25185],
      [11, 16450],
      [12, 12645],
      [13, 12248],
      [14, 17956],
      [15, 26991],
      [16, 28897],
      [17, 21697],
      [18, 12352],
      [19, 5403],
      [20, 2428],
      [21, 1193],
      [22, 643],
      [23, 416]
    ]
  },
  {
    "City": "Edinburgh",
    "Category": "All",
    "checkin":[
      [0, 1282],
      [1, 1633],
      [2, 2093],
      [3, 2657],
      [4, 4573],
      [5, 5655],
      [6, 4871],
      [7, 4320],
      [8, 4005],
      [9, 4880],
      [10, 5920],
      [11, 5663],
      [12, 4685],
      [13, 3280],
      [14, 2216],
      [15, 1424],
      [16, 678],
      [17, 253],
      [18, 76],
      [19, 45],
      [20, 53],
      [21, 110],
      [22, 238],
      [23, 459]
    ],
    "food":[
      [0, 701],
      [1, 933],
      [2, 1129],
      [3, 1451],
      [4, 2485],
      [5, 3175],
      [6, 2531],
      [7, 2045],
      [8, 1651],
      [9, 1868],
      [10, 2269],
      [11, 2245],
      [12, 1769],
      [13, 1110],
      [14, 628],
      [15, 304],
      [16, 162],
      [17, 58],
      [18, 18],
      [19, 15],
      [20, 8],
      [21, 15],
      [22, 42],
      [23, 192]
    ]
  },
  {
    "City": "Kalsruhe",
    "Category": "All",
    "checkin":[
      [0, 21],
      [1, 33],
      [2, 66],
      [3, 142],
      [4, 102],
      [5, 96],
      [6, 62],
      [7, 71],
      [8, 85],
      [9, 130],
      [10, 167],
      [11, 148],
      [12, 104],
      [13, 77],
      [14, 77],
      [15, 32],
      [16, 8],
      [17, 2],
      [18, 0],
      [19, 1],
      [20, 4],
      [21, 5],
      [22, 7],
      [23, 21]
    ],
    "food":[
      [0, 10],
      [1, 12],
      [2, 42],
      [3, 103],
      [4, 80],
      [5, 53],
      [6, 40],
      [7, 43],
      [8, 49],
      [9, 83],
      [10, 102],
      [11, 90],
      [12, 78],
      [13, 50],
      [14, 19],
      [15, 8],
      [16, 4],
      [17, 0],
      [18, 0],
      [19, 0],
      [20, 0],
      [21, 1],
      [22, 1],
      [23, 6]
    ]
  },
  {
    "City": "Madison",
    "Category": "All",
    "checkin":[
      [0, 361],
      [1, 136],
      [2, 103],
      [3, 309],
      [4, 910],
      [5, 2031],
      [6, 2647],
      [7, 3465],
      [8, 4659],
      [9, 7161],
      [10, 9921],
      [11, 8401],
      [12, 6492],
      [13, 5591],
      [14, 6089],
      [15, 9195],
      [16, 12669],
      [17, 12557],
      [18, 9433],
      [19, 6065],
      [20, 3570],
      [21, 2434],
      [22, 1436],
      [23, 734]
    ],
    "food":[
      [0, 277],
      [1, 89],
      [2, 31],
      [3, 109],
      [4, 457],
      [5, 1516],
      [6, 1970],
      [7, 2536],
      [8, 3222],
      [9, 4837],
      [10, 6876],
      [11, 5555],
      [12, 3922],
      [13, 3170],
      [14, 3444],
      [15, 5616],
      [16, 7662],
      [17, 7529],
      [18, 5347],
      [19, 3127],
      [20, 1581],
      [21, 1024],
      [22, 613],
      [23, 354]
    ]
  },
  {
    "City": "Montreal",
    "Category": "All",
    "checkin":[
      [0, 414],
      [1, 154],
      [2, 161],
      [3, 372],
      [4, 934],
      [5, 2060],
      [6, 3485],
      [7, 4890],
      [8, 7054],
      [9, 10944],
      [10, 10381],
      [11, 8819],
      [12, 8197],
      [13, 7884],
      [14, 9533],
      [15, 12006],
      [16, 12494],
      [17, 11417],
      [18, 9102],
      [19, 6136],
      [20, 3960],
      [21, 2446],
      [22, 1429],
      [23, 772]
    ],
    "food":[
      [0, 257],
      [1, 93],
      [2, 65],
      [3, 189],
      [4, 569],
      [5, 1409],
      [6, 2563],
      [7, 3658],
      [8, 5248],
      [9, 8347],
      [10, 7739],
      [11, 6317],
      [12, 5507],
      [13, 4953],
      [14, 5889],
      [15, 7635],
      [16, 7878],
      [17, 7399],
      [18, 5661],
      [19, 3506],
      [20, 1981],
      [21, 1112],
      [22, 583],
      [23, 350]
    ]
  },
  {
    "City": "Phoenix",
    "Category": "All",
    "checkin":[
      [0, 7492],
      [1, 3403],
      [2, 1400],
      [3, 1254],
      [4, 4682],
      [5, 11169],
      [6, 21169],
      [7, 35442],
      [8, 46121],
      [9, 52701],
      [10, 70533],
      [11, 104867],
      [12, 111488],
      [13, 85853],
      [14, 69886],
      [15, 67296],
      [16, 83884],
      [17, 114113],
      [18, 125105],
      [19, 105527],
      [20, 71116],
      [21, 43651],
      [22, 25111],
      [23, 13860]

    ],
    "food":[
      [0, 2096],
      [1, 1205],
      [2, 729],
      [3, 421],
      [4, 1265],
      [5, 3778],
      [6, 10326],
      [7, 19696],
      [8, 24803],
      [9, 28573],
      [10, 40811],
      [11, 66790],
      [12, 70157],
      [13, 48627],
      [14, 35351],
      [15, 31427],
      [16, 40516],
      [17, 59586],
      [18, 68074],
      [19, 58103],
      [20, 37151],
      [21, 18527],
      [22, 8137],
      [23, 3892]
    ]
  },
  {
    "City": "Pittsburgh",
    "Category": "All",
    "checkin":[
      [0, 208],
      [1, 181],
      [2, 408],
      [3, 1480],
      [4, 3405],
      [5, 5255],
      [6, 6941],
      [7, 8451],
      [8, 14853],
      [9, 22842],
      [10, 18753],
      [11, 14348],
      [12, 11873],
      [13, 12775],
      [14, 18682],
      [15, 24559],
      [16, 24954],
      [17, 18929],
      [18, 12452],
      [19, 7446],
      [20, 4653],
      [21, 2857],
      [22, 1340],
      [23, 515]
    ],
    "food":[
      [0, 85],
      [1, 73],
      [2, 135],
      [3, 748],
      [4, 2315],
      [5, 3549],
      [6, 4803],
      [7, 5749],
      [8, 10073],
      [9, 15885],
      [10, 12300],
      [11, 8661],
      [12, 6835],
      [13, 6802],
      [14, 10489],
      [15, 13776],
      [16, 13786],
      [17, 10857],
      [18, 6594],
      [19, 3363],
      [20, 1776],
      [21, 966],
      [22, 522],
      [23, 236]
    ]
  },
  {
    "City": "Urbana",
    "Category": "All",
    "checkin":[
      [0, 84],
      [1, 32],
      [2, 20],
      [3, 14],
      [4, 76],
      [5, 186],
      [6, 343],
      [7, 509],
      [8, 694],
      [9, 1669],
      [10, 2807],
      [11, 2039],
      [12, 1402],
      [13, 1195],
      [14, 1208],
      [15, 2154],
      [16, 2875],
      [17, 2685],
      [18, 1957],
      [19, 1229],
      [20, 774],
      [21, 520],
      [22, 335],
      [23, 185]
    ],
    "food":[
      [0, 53],
      [1, 21],
      [2, 15],
      [3, 11],
      [4, 44],
      [5, 132],
      [6, 252],
      [7, 390],
      [8, 517],
      [9, 1271],
      [10, 2176],
      [11, 1578],
      [12, 1061],
      [13, 866],
      [14, 834],
      [15, 1369],
      [16, 1848],
      [17, 1734],
      [18, 1178],
      [19, 666],
      [20, 303],
      [21, 201],
      [22, 144],
      [23, 93]
    ]
  },
  {
    "City": "Waterloo",
    "Category": "All",
    "checkin":[
      [0, 52],
      [1, 12],
      [2, 32],
      [3, 60],
      [4, 83],
      [5, 105],
      [6, 156],
      [7, 168],
      [8, 311],
      [9, 587],
      [10, 442],
      [11, 381],
      [12, 292],
      [13, 284],
      [14, 571],
      [15, 365],
      [16, 642],
      [17, 445],
      [18, 325],
      [19, 204],
      [20, 117],
      [21, 99],
      [22, 25],
      [23, 27]
    ],
    "food":[
      [0, 43],
      [1, 7],
      [2, 24],
      [3, 46],
      [4, 56],
      [5, 67],
      [6, 97],
      [7, 130],
      [8, 238],
      [9, 439],
      [10, 350],
      [11, 279],
      [12, 218],
      [13, 211],
      [14, 430],
      [15, 298],
      [16, 493],
      [17, 356],
      [18, 239],
      [19, 113],
      [20, 71],
      [21, 56],
      [22, 21],
      [23, 21]
    ]
  }
]
